openph_solar/__init__.py
openph_solar/calc_periods.py
openph_solar/get_solvers.py
openph_solar/solvers.py
openph_solar-0.1.2.dist-info/WHEEL
openph_solar-0.1.2.dist-info/entry_points.txt
openph_solar-0.1.2.dist-info/METADATA
openph_solar-0.1.2.dist-info/RECORD
