Metadata-Version: 2.3
Name: openph-solar
Version: 0.1.2
Summary: OpenPH Solar - Solar radiation and shading calculations for Passive House
Author: PH-Tools
Author-email: PH-Tools <none@none.com>
License: GNU GENERAL PUBLIC LICENSE
Requires-Dist: openph
Requires-Dist: phx
Requires-Dist: ph-units
Requires-Dist: honeybee-ph
Requires-Dist: pytest>=8.4.2 ; extra == 'dev'
Requires-Dist: openpyxl>=3.1.5 ; extra == 'dev'
Requires-Dist: rich>=14.2.0 ; extra == 'dev'
Requires-Python: >=3.10
Provides-Extra: dev
Provides-Extra: workspace
